{
  "module": {
    "name": "entry",
    "type": "entry",
    "srcEntrance": "./ets/Application/AbilityStage.ts",
    "description": "$string:entry_desc",
    "mainElement": "MainAbility",
    "deviceTypes": [
      "default",
      "tablet"
    ],
    "deliveryWithInstall": true,
    "installationFree": false,
    "pages": "$profile:main_pages",
    "uiSyntax": "ets",
    "abilities": [
      {
        "name": "com.example.myapplication.hmservice.MainAbility",
        "srcEntrance": "./ets/MainAbility/MainAbility.ts",
        "description": "$string:MainAbility_desc",
        "icon": "$media:icon",
        "label": "$string:MainAbility_label",
        "visible": true,
		"orientation": "portrait",
        "skills": [
          {
            "entities": [
              "entity.system.home"
            ],
            "actions": [
              "action.system.home"
            ]
          }
        ]
      },
      {
        "name": "com.example.myapplication.MainAbility2",
        "srcEntrance": "./ets/MainAbility2/MainAbility2.ts",
        "description": "$string:MainAbility2_desc",
        "icon": "$media:icon",
        "label": "$string:MainAbility2_label"
      }
    ],
    "extensionAbilities": [
      {
        "name": "com.example.myapplication.ServiceAbility",
        "srcEntrance": "./ets/ServiceAbility/ServiceAbility.ts",
        "label": "$string:form_ServiceAbility_label",
        "description": "$string:form_ServiceAbility_desc",
        "type": "service"
      },
      {
        "name": "com.example.myapplication.ServiceAbility2",
        "srcEntrance": "./ets/ServiceAbility2/ServiceAbility2.ts",
        "label": "$string:form_ServiceAbility2_label",
        "description": "$string:form_ServiceAbility2_desc",
        "type": "service"
      },
      {
        "name": "com.example.myapplication.ServiceAbility3",
        "srcEntrance": "./ets/ServiceAbility3/ServiceAbility3.ts",
        "label": "$string:form_ServiceAbility3_label",
        "description": "$string:form_ServiceAbility3_desc",
        "type": "service"
      },
      {
        "name": "com.example.myapplication.ServiceAbility4",
        "srcEntrance": "./ets/ServiceAbility4/ServiceAbility4.ts",
        "label": "$string:form_ServiceAbility4_label",
        "description": "$string:form_ServiceAbility4_desc",
        "type": "service"
      },
      {
        "name": "com.example.myapplication.ServiceAbility5",
        "srcEntrance": "./ets/ServiceAbility5/ServiceAbility5.ts",
        "label": "$string:form_ServiceAbility5_label",
        "description": "$string:form_ServiceAbility5_desc",
        "type": "service"
      },
      {
        "name": "com.example.myapplication.ServiceAbility6",
        "srcEntrance": "./ets/ServiceAbility6/ServiceAbility6.ts",
        "label": "$string:form_ServiceAbility6_label",
        "description": "$string:form_ServiceAbility6_desc",
        "type": "service"
      },
      {
        "name": "com.example.myapplication.ServiceAbility7",
        "srcEntrance": "./ets/ServiceAbility7/ServiceAbility7.ts",
        "label": "$string:form_ServiceAbility7_label",
        "description": "$string:form_ServiceAbility7_desc",
        "type": "service"
      },
      {
        "name": "com.example.myapplication.ServiceAbility8",
        "srcEntrance": "./ets/ServiceAbility8/ServiceAbility8.ts",
        "label": "$string:form_ServiceAbility8_label",
        "description": "$string:form_ServiceAbility8_desc",
        "type": "service"
      },
      {
        "name": "com.example.myapplication.ServiceAbility9",
        "srcEntrance": "./ets/ServiceAbility9/ServiceAbility9.ts",
        "label": "$string:form_ServiceAbility9_label",
        "description": "$string:form_ServiceAbility9_desc",
        "type": "service"
      }
    ],
    "requestPermissions": [
      {
        "name": "ohos.permission.GET_BUNDLE_INFO"
      }
    ]
  }
}